[
	{
		"country": "Egypt",
		"capital": "Cairo",
		"wrong1": "Riyadh",
		"wrong2": "Athens",
		"wrong3": "Istanbul",
		"wrong4": "Dubai",
		"wrong5": "Jerusalem",
		"wrong6": "Rome",
		"wrong7": "Berlin",
		"wrong8": "Paris",
		"wrong9": "London",
		"wrong10": "Madrid",
		"wrong11": "Ottawa",
		"wrong12": "Vienna",
		"wrong13": "Brussels",
		"wrong14": "Stockholm",
		"wrong15": "Warsaw",
		"wrong16": "Oslo",
		"wrong17": "Amsterdam",
		"wrong18": "Copenhagen",
		"wrong19": "Dublin",
		"wrong20": "Helsinki",
		"wrong21": "New Delhi",
		"wrong22": "Tokyo",
		"wrong23": "Beijing",
		"wrong24": "Moscow",
		"wrong25": "Brasilia"
	},
	{
		"country": "France",
		"capital": "Paris",
		"wrong1": "London",
		"wrong2": "Berlin",
		"wrong3": "Rome",
		"wrong4": "Madrid",
		"wrong5": "Vienna",
		"wrong6": "Brussels",
		"wrong7": "Amsterdam",
		"wrong8": "Stockholm",
		"wrong9": "Oslo",
		"wrong10": "Lisbon",
		"wrong11": "Athens",
		"wrong12": "Istanbul",
		"wrong13": "Dublin",
		"wrong14": "Helsinki",
		"wrong15": "Warsaw",
		"wrong16": "Copenhagen",
		"wrong17": "New Delhi",
		"wrong18": "Tokyo",
		"wrong19": "Beijing",
		"wrong20": "Moscow",
		"wrong21": "Brasilia",
		"wrong22": "Ottawa",
		"wrong23": "Seoul",
		"wrong24": "Dubai",
		"wrong25": "Jerusalem"
	},
	{
		"country": "Japan",
		"capital": "Tokyo",
		"wrong1": "Seoul",
		"wrong2": "Beijing",
		"wrong3": "Hanoi",
		"wrong4": "Manila",
		"wrong5": "Singapore",
		"wrong6": "Bangkok",
		"wrong7": "Kuala Lumpur",
		"wrong8": "Jakarta",
		"wrong9": "Delhi",
		"wrong10": "Hong Kong",
		"wrong11": "Taipei",
		"wrong12": "Mumbai",
		"wrong13": "Yangon",
		"wrong14": "Vientiane",
		"wrong15": "Phnom Penh",
		"wrong16": "Kathmandu",
		"wrong17": "Ulaanbaatar",
		"wrong18": "Wellington",
		"wrong19": "Sydney",
		"wrong20": "Auckland",
		"wrong21": "Dubai",
		"wrong22": "Jerusalem",
		"wrong23": "Riyadh",
		"wrong24": "Istanbul",
		"wrong25": "Athens"
	},
	{
		"country": "Germany",
		"capital": "Berlin",
		"wrong1": "Vienna",
		"wrong2": "Zurich",
		"wrong3": "Amsterdam",
		"wrong4": "Paris",
		"wrong5": "Madrid",
		"wrong6": "Brussels",
		"wrong7": "Rome",
		"wrong8": "London",
		"wrong9": "Copenhagen",
		"wrong10": "Stockholm",
		"wrong11": "Oslo",
		"wrong12": "Lisbon",
		"wrong13": "Athens",
		"wrong14": "Warsaw",
		"wrong15": "Budapest",
		"wrong16": "Bucharest",
		"wrong17": "Belgrade",
		"wrong18": "Prague",
		"wrong19": "Moscow",
		"wrong20": "Beijing",
		"wrong21": "Tokyo",
		"wrong22": "New Delhi",
		"wrong23": "Seoul",
		"wrong24": "Dubai",
		"wrong25": "Jerusalem"
	},
	{
		"country": "Brazil",
		"capital": "Brasilia",
		"wrong1": "Buenos Aires",
		"wrong2": "Lima",
		"wrong3": "Santiago",
		"wrong4": "Bogotá",
		"wrong5": "Quito",
		"wrong6": "Caracas",
		"wrong7": "Montevideo",
		"wrong8": "Asunción",
		"wrong9": "La Paz",
		"wrong10": "Georgetown",
		"wrong11": "Paramaribo",
		"wrong12": "Port of Spain",
		"wrong13": "Kingston",
		"wrong14": "Havana",
		"wrong15": "San Salvador",
		"wrong16": "Guatemala City",
		"wrong17": "Managua",
		"wrong18": "Tegucigalpa",
		"wrong19": "Belmopan",
		"wrong20": "Nassau",
		"wrong21": "Port-au-Prince",
		"wrong22": "Haiti",
		"wrong23": "Washington, D.C.",
		"wrong24": "Mexico City",
		"wrong25": "San Juan"
	},
	{
		"country": "Canada",
		"capital": "Ottawa",
		"wrong1": "Toronto",
		"wrong2": "Vancouver",
		"wrong3": "Montreal",
		"wrong4": "Calgary",
		"wrong5": "Edmonton",
		"wrong6": "Halifax",
		"wrong7": "Victoria",
		"wrong8": "Winnipeg",
		"wrong9": "Quebec City",
		"wrong10": "St. John's",
		"wrong11": "London",
		"wrong12": "Paris",
		"wrong13": "New York",
		"wrong14": "San Francisco",
		"wrong15": "Chicago",
		"wrong16": "Boston",
		"wrong17": "Seattle",
		"wrong18": "Los Angeles",
		"wrong19": "Houston",
		"wrong20": "Miami",
		"wrong21": "Washington, D.C.",
		"wrong22": "Philadelphia",
		"wrong23": "Dallas",
		"wrong24": "Atlanta",
		"wrong25": "Denver"
	},
	{
		"country": "Australia",
		"capital": "Canberra",
		"wrong1": "Sydney",
		"wrong2": "Melbourne",
		"wrong3": "Brisbane",
		"wrong4": "Perth",
		"wrong5": "Adelaide",
		"wrong6": "Hobart",
		"wrong7": "Darwin",
		"wrong8": "Gold Coast",
		"wrong9": "Newcastle",
		"wrong10": "Cairns",
		"wrong11": "Auckland",
		"wrong12": "Wellington",
		"wrong13": "Sydney",
		"wrong14": "Christchurch",
		"wrong15": "Melbourne",
		"wrong16": "Hobart",
		"wrong17": "Brisbane",
		"wrong18": "Perth",
		"wrong19": "Darwin",
		"wrong20": "Adelaide",
		"wrong21": "Canberra",
		"wrong22": "Port Moresby",
		"wrong23": "Fiji",
		"wrong24": "Honolulu",
		"wrong25": "Apia"
	},
	{
		"country": "Italy",
		"capital": "Rome",
		"wrong1": "Milan",
		"wrong2": "Florence",
		"wrong3": "Venice",
		"wrong4": "Naples",
		"wrong5": "Turin",
		"wrong6": "Genoa",
		"wrong7": "Bologna",
		"wrong8": "Palermo",
		"wrong9": "Catania",
		"wrong10": "Trieste",
		"wrong11": "Paris",
		"wrong12": "Madrid",
		"wrong13": "London",
		"wrong14": "Berlin",
		"wrong15": "Vienna",
		"wrong16": "Zurich",
		"wrong17": "Brussels",
		"wrong18": "Amsterdam",
		"wrong19": "Athens",
		"wrong20": "Istanbul",
		"wrong21": "Copenhagen",
		"wrong22": "Stockholm",
		"wrong23": "Oslo",
		"wrong24": "Helsinki",
		"wrong25": "Lisbon"
	},
	{
		"country": "United States",
		"capital": "Washington",
		"wrong1": "New York",
		"wrong2": "Los Angeles",
		"wrong3": "Chicago",
		"wrong4": "San Francisco",
		"wrong5": "Miami",
		"wrong6": "Houston",
		"wrong7": "Philadelphia",
		"wrong8": "Dallas",
		"wrong9": "Atlanta",
		"wrong10": "Boston",
		"wrong11": "London",
		"wrong12": "Paris",
		"wrong13": "Toronto",
		"wrong14": "Mexico City",
		"wrong15": "Vancouver",
		"wrong16": "Montreal",
		"wrong17": "San Juan",
		"wrong18": "Buenos Aires",
		"wrong19": "Brasilia",
		"wrong20": "Santiago",
		"wrong21": "Lima",
		"wrong22": "Bogotá",
		"wrong23": "Quito",
		"wrong24": "Caracas",
		"wrong25": "Georgetown"
	},
	{
		"country": "United Kingdom",
		"capital": "London",
		"wrong1": "Edinburgh",
		"wrong2": "Manchester",
		"wrong3": "Birmingham",
		"wrong4": "Glasgow",
		"wrong5": "Liverpool",
		"wrong6": "Bristol",
		"wrong7": "Leeds",
		"wrong8": "Sheffield",
		"wrong9": "Newcastle",
		"wrong10": "Cardiff",
		"wrong11": "Dublin",
		"wrong12": "Paris",
		"wrong13": "Berlin",
		"wrong14": "Amsterdam",
		"wrong15": "Brussels",
		"wrong16": "Edinburgh",
		"wrong17": "Aberdeen",
		"wrong18": "Inverness",
		"wrong19": "Glasgow",
		"wrong20": "Derry",
		"wrong21": "Belfast",
		"wrong22": "Wales",
		"wrong23": "London",
		"wrong24": "York",
		"wrong25": "Cambridge"
	},
	{
		"country": "China",
		"capital": "Beijing",
		"wrong1": "Shanghai",
		"wrong2": "Hong Kong",
		"wrong3": "Guangzhou",
		"wrong4": "Shenzhen",
		"wrong5": "Chengdu",
		"wrong6": "Wuhan",
		"wrong7": "Xi'an",
		"wrong8": "Hangzhou",
		"wrong9": "Nanjing",
		"wrong10": "Harbin",
		"wrong11": "Seoul",
		"wrong12": "Tokyo",
		"wrong13": "Moscow",
		"wrong14": "Singapore",
		"wrong15": "Taipei",
		"wrong16": "Manila",
		"wrong17": "Bangkok",
		"wrong18": "Hanoi",
		"wrong19": "Kuala Lumpur",
		"wrong20": "Ho Chi Minh City",
		"wrong21": "Delhi",
		"wrong22": "Jakarta",
		"wrong23": "Mumbai",
		"wrong24": "Sydney",
		"wrong25": "Melbourne"
	},
	{
		"country": "Russia",
		"capital": "Moscow",
		"wrong1": "St. Petersburg",
		"wrong2": "Novosibirsk",
		"wrong3": "Yekaterinburg",
		"wrong4": "Nizhny Novgorod",
		"wrong5": "Kazan",
		"wrong6": "Omsk",
		"wrong7": "Samara",
		"wrong8": "Rostov-on-Don",
		"wrong9": "Ufa",
		"wrong10": "Volgograd",
		"wrong11": "Beijing",
		"wrong12": "Seoul",
		"wrong13": "Tokyo",
		"wrong14": "Istanbul",
		"wrong15": "Warsaw",
		"wrong16": "Minsk",
		"wrong17": "Riga",
		"wrong18": "Tallinn",
		"wrong19": "Vilnius",
		"wrong20": "Helsinki",
		"wrong21": "Oslo",
		"wrong22": "Kyiv",
		"wrong23": "Bucharest",
		"wrong24": "Budapest",
		"wrong25": "Belgrade"
	},
	{
		"country": "India",
		"capital": "New Delhi",
		"wrong1": "Mumbai",
		"wrong2": "Kolkata",
		"wrong3": "Bangalore",
		"wrong4": "Chennai",
		"wrong5": "Hyderabad",
		"wrong6": "Ahmedabad",
		"wrong7": "Pune",
		"wrong8": "Jaipur",
		"wrong9": "Surat",
		"wrong10": "Lucknow",
		"wrong11": "Islamabad",
		"wrong12": "Dhaka",
		"wrong13": "Kathmandu",
		"wrong14": "Colombo",
		"wrong15": "Male",
		"wrong16": "Kathmandu",
		"wrong17": "Thimphu",
		"wrong18": "Lhasa",
		"wrong19": "Yangon",
		"wrong20": "Vientiane",
		"wrong21": "Hanoi",
		"wrong22": "Ho Chi Minh City",
		"wrong23": "Jakarta",
		"wrong24": "Manila",
		"wrong25": "Singapore"
	},
	{
		"country": "Spain",
		"capital": "Madrid",
		"wrong1": "Barcelona",
		"wrong2": "Seville",
		"wrong3": "Valencia",
		"wrong4": "Bilbao",
		"wrong5": "Malaga",
		"wrong6": "Granada",
		"wrong7": "San Sebastián",
		"wrong8": "Alicante",
		"wrong9": "Murcia",
		"wrong10": "Zaragoza",
		"wrong11": "Paris",
		"wrong12": "Lisbon",
		"wrong13": "Rome",
		"wrong14": "London",
		"wrong15": "Berlin",
		"wrong16": "Madrid",
		"wrong17": "Vienna",
		"wrong18": "Brussels",
		"wrong19": "Amsterdam",
		"wrong20": "Athens",
		"wrong21": "Moscow",
		"wrong22": "New Delhi",
		"wrong23": "Tokyo",
		"wrong24": "Beijing",
		"wrong25": "Washington, D.C."
	},
	{
		"country": "Netherlands",
		"capital": "Amsterdam",
		"wrong1": "Rotterdam",
		"wrong2": "The Hague",
		"wrong3": "Utrecht",
		"wrong4": "Eindhoven",
		"wrong5": "Groningen",
		"wrong6": "Maastricht",
		"wrong7": "Haarlem",
		"wrong8": "Nijmegen",
		"wrong9": "Leiden",
		"wrong10": "Enschede",
		"wrong11": "Brussels",
		"wrong12": "Antwerp",
		"wrong13": "Paris",
		"wrong14": "London",
		"wrong15": "Berlin",
		"wrong16": "Brussels",
		"wrong17": "Zurich",
		"wrong18": "Geneva",
		"wrong19": "Vienna",
		"wrong20": "Madrid",
		"wrong21": "Rome",
		"wrong22": "Athens",
		"wrong23": "Stockholm",
		"wrong24": "Oslo",
		"wrong25": "Copenhagen"
	},
	{
		"country": "Switzerland",
		"capital": "Bern",
		"wrong1": "Zurich",
		"wrong2": "Geneva",
		"wrong3": "Basel",
		"wrong4": "Lausanne",
		"wrong5": "Lucerne",
		"wrong6": "St. Moritz",
		"wrong7": "Zurich",
		"wrong8": "Neuchâtel",
		"wrong9": "Jungfrau",
		"wrong10": "Zermatt",
		"wrong11": "Paris",
		"wrong12": "Vienna",
		"wrong13": "Berlin",
		"wrong14": "Brussels",
		"wrong15": "London",
		"wrong16": "Rome",
		"wrong17": "Madrid",
		"wrong18": "Stockholm",
		"wrong19": "Amsterdam",
		"wrong20": "Oslo",
		"wrong21": "Helsinki",
		"wrong22": "Athens",
		"wrong23": "Dublin",
		"wrong24": "Lisbon",
		"wrong25": "Budapest"
	},
	{
		"country": "Sweden",
		"capital": "Stockholm",
		"wrong1": "Gothenburg",
		"wrong2": "Malmö",
		"wrong3": "Uppsala",
		"wrong4": "Lund",
		"wrong5": "Linköping",
		"wrong6": "Örebro",
		"wrong7": "Helsingborg",
		"wrong8": "Västerås",
		"wrong9": "Jönköping",
		"wrong10": "Sundsvall",
		"wrong11": "Oslo",
		"wrong12": "Copenhagen",
		"wrong13": "Helsinki",
		"wrong14": "Tallinn",
		"wrong15": "Riga",
		"wrong16": "Vilnius",
		"wrong17": "London",
		"wrong18": "Paris",
		"wrong19": "Berlin",
		"wrong20": "Amsterdam",
		"wrong21": "Brussels",
		"wrong22": "Vienna",
		"wrong23": "Zurich",
		"wrong24": "Madrid",
		"wrong25": "Rome"
	},
	{
		"country": "Turkey",
		"capital": "Ankara",
		"wrong1": "Istanbul",
		"wrong2": "Izmir",
		"wrong3": "Antalya",
		"wrong4": "Bursa",
		"wrong5": "Adana",
		"wrong6": "Konya",
		"wrong7": "Gaziantep",
		"wrong8": "Mersin",
		"wrong9": "Kayseri",
		"wrong10": "Samsun",
		"wrong11": "Athens",
		"wrong12": "Dubai",
		"wrong13": "Tehran",
		"wrong14": "Cairo",
		"wrong15": "Jerusalem",
		"wrong16": "Beirut",
		"wrong17": "Baku",
		"wrong18": "Tbilisi",
		"wrong19": "Yerevan",
		"wrong20": "Riyadh",
		"wrong21": "Istanbul",
		"wrong22": "Rome",
		"wrong23": "Vienna",
		"wrong24": "Paris",
		"wrong25": "Berlin"
	},
	{
		"country": "South Korea",
		"capital": "Seoul",
		"wrong1": "Busan",
		"wrong2": "Incheon",
		"wrong3": "Daegu",
		"wrong4": "Daejeon",
		"wrong5": "Gwangju",
		"wrong6": "Jeju",
		"wrong7": "Suwon",
		"wrong8": "Ulsan",
		"wrong9": "Changwon",
		"wrong10": "Jeonju",
		"wrong11": "Tokyo",
		"wrong12": "Beijing",
		"wrong13": "Shanghai",
		"wrong14": "Hanoi",
		"wrong15": "Manila",
		"wrong16": "Bangkok",
		"wrong17": "Hong Kong",
		"wrong18": "Taipei",
		"wrong19": "Singapore",
		"wrong20": "Kuala Lumpur",
		"wrong21": "Jakarta",
		"wrong22": "Ho Chi Minh City",
		"wrong23": "Delhi",
		"wrong24": "Mumbai",
		"wrong25": "Sydney"
	},
	{
		"country": "Greece",
		"capital": "Athens",
		"wrong1": "Thessaloniki",
		"wrong2": "Patras",
		"wrong3": "Heraklion",
		"wrong4": "Larissa",
		"wrong5": "Volos",
		"wrong6": "Chania",
		"wrong7": "Rhodes",
		"wrong8": "Kalamata",
		"wrong9": "Ioannina",
		"wrong10": "Kavala",
		"wrong11": "Athens",
		"wrong12": "Rome",
		"wrong13": "Istanbul",
		"wrong14": "Cairo",
		"wrong15": "Berlin",
		"wrong16": "Paris",
		"wrong17": "Madrid",
		"wrong18": "Vienna",
		"wrong19": "Stockholm",
		"wrong20": "Zurich",
		"wrong21": "London",
		"wrong22": "Lisbon",
		"wrong23": "Brussels",
		"wrong24": "Amsterdam",
		"wrong25": "Dublin"
	},
	{
		"country": "Poland",
		"capital": "Warsaw",
		"wrong1": "Kraków",
		"wrong2": "Łódź",
		"wrong3": "Wrocław",
		"wrong4": "Gdańsk",
		"wrong5": "Poznań",
		"wrong6": "Szczecin",
		"wrong7": "Bydgoszcz",
		"wrong8": "Lublin",
		"wrong9": "Katowice",
		"wrong10": "Białystok",
		"wrong11": "Berlin",
		"wrong12": "Prague",
		"wrong13": "Bratislava",
		"wrong14": "Budapest",
		"wrong15": "Vienna",
		"wrong16": "Kyiv",
		"wrong17": "Minsk",
		"wrong18": "Vilnius",
		"wrong19": "Riga",
		"wrong20": "Tallinn",
		"wrong21": "Helsinki",
		"wrong22": "Oslo",
		"wrong23": "Brussels",
		"wrong24": "Copenhagen",
		"wrong25": "Stockholm"
	},
	{
		"country": "Portugal",
		"capital": "Lisbon",
		"wrong1": "Porto",
		"wrong2": "Braga",
		"wrong3": "Coimbra",
		"wrong4": "Aveiro",
		"wrong5": "Funchal",
		"wrong6": "Évora",
		"wrong7": "Guimarães",
		"wrong8": "Viseu",
		"wrong9": "Setúbal",
		"wrong10": "Leiria",
		"wrong11": "Madrid",
		"wrong12": "Seville",
		"wrong13": "Barcelona",
		"wrong14": "Paris",
		"wrong15": "Madrid",
		"wrong16": "Rome",
		"wrong17": "London",
		"wrong18": "Brussels",
		"wrong19": "Vienna",
		"wrong20": "Berlin",
		"wrong21": "Zurich",
		"wrong22": "Amsterdam",
		"wrong23": "Stockholm",
		"wrong24": "Helsinki",
		"wrong25": "Dublin"
	},
	{
		"country": "Belgium",
		"capital": "Brussels",
		"wrong1": "Antwerp",
		"wrong2": "Ghent",
		"wrong3": "Bruges",
		"wrong4": "Leuven",
		"wrong5": "Namur",
		"wrong6": "Liege",
		"wrong7": "Oostende",
		"wrong8": "Mechelen",
		"wrong9": "Hasselt",
		"wrong10": "Charleroi",
		"wrong11": "Paris",
		"wrong12": "Amsterdam",
		"wrong13": "Luxembourg",
		"wrong14": "London",
		"wrong15": "Berlin",
		"wrong16": "Brussels",
		"wrong17": "Zurich",
		"wrong18": "Vienna",
		"wrong19": "Stockholm",
		"wrong20": "Rome",
		"wrong21": "Madrid",
		"wrong22": "Dublin",
		"wrong23": "Copenhagen",
		"wrong24": "Oslo",
		"wrong25": "Helsinki"
	},
	{
		"country": "Austria",
		"capital": "Vienna",
		"wrong1": "Salzburg",
		"wrong2": "Graz",
		"wrong3": "Linz",
		"wrong4": "Innsbruck",
		"wrong5": "Klagenfurt",
		"wrong6": "Villach",
		"wrong7": "St. Pölten",
		"wrong8": "Wels",
		"wrong9": "Steyr",
		"wrong10": "Bregenz",
		"wrong11": "Zurich",
		"wrong12": "Geneva",
		"wrong13": "Bern",
		"wrong14": "Munich",
		"wrong15": "Budapest",
		"wrong16": "Prague",
		"wrong17": "Ljubljana",
		"wrong18": "Milan",
		"wrong19": "Vienna",
		"wrong20": "Rome",
		"wrong21": "Bratislava",
		"wrong22": "Salzburg",
		"wrong23": "Ljubljana",
		"wrong24": "Zürich",
		"wrong25": "Geneva"
	},
	{
		"country": "Norway",
		"capital": "Oslo",
		"wrong1": "Bergen",
		"wrong2": "Stavanger",
		"wrong3": "Trondheim",
		"wrong4": "Drammen",
		"wrong5": "Kristiansand",
		"wrong6": "Tromsø",
		"wrong7": "Ålesund",
		"wrong8": "Haugesund",
		"wrong9": "Sandnes",
		"wrong10": "Porsgrunn",
		"wrong11": "Stockholm",
		"wrong12": "Copenhagen",
		"wrong13": "Helsinki",
		"wrong14": "Oslo",
		"wrong15": "Bergen",
		"wrong16": "Tromsø",
		"wrong17": "Reykjavik",
		"wrong18": "Helsinki",
		"wrong19": "Tallinn",
		"wrong20": "Riga",
		"wrong21": "Vilnius",
		"wrong22": "Stockholm",
		"wrong23": "Moscow",
		"wrong24": "Oslo",
		"wrong25": "Lofoten"
	},
	{
		"country": "Denmark",
		"capital": "Copenhagen",
		"wrong1": "Aarhus",
		"wrong2": "Odense",
		"wrong3": "Aalborg",
		"wrong4": "Esbjerg",
		"wrong5": "Randers",
		"wrong6": "Kolding",
		"wrong7": "Herning",
		"wrong8": "Horsens",
		"wrong9": "Vejle",
		"wrong10": "Silkeborg",
		"wrong11": "Stockholm",
		"wrong12": "Oslo",
		"wrong13": "Helsinki",
		"wrong14": "Berlin",
		"wrong15": "Amsterdam",
		"wrong16": "Brussels",
		"wrong17": "Vienna",
		"wrong18": "Copenhagen",
		"wrong19": "Zurich",
		"wrong20": "Geneva",
		"wrong21": "Prague",
		"wrong22": "Budapest",
		"wrong23": "Ljubljana",
		"wrong24": "Warsaw",
		"wrong25": "Moscow"
	},
	{
		"country": "Ireland",
		"capital": "Dublin",
		"wrong1": "Cork",
		"wrong2": "Limerick",
		"wrong3": "Galway",
		"wrong4": "Waterford",
		"wrong5": "Kilkenny",
		"wrong6": "Tralee",
		"wrong7": "Sligo",
		"wrong8": "Wexford",
		"wrong9": "Ennis",
		"wrong10": "Drogheda",
		"wrong11": "Edinburgh",
		"wrong12": "London",
		"wrong13": "Glasgow",
		"wrong14": "Belfast",
		"wrong15": "Cardiff",
		"wrong16": "Derry",
		"wrong17": "Aberdeen",
		"wrong18": "Inverness",
		"wrong19": "Manchester",
		"wrong20": "Liverpool",
		"wrong21": "Dublin",
		"wrong22": "Londonderry",
		"wrong23": "Belfast",
		"wrong24": "Brussels",
		"wrong25": "Derry"
	},
	{
		"country": "New Zealand",
		"capital": "Wellington",
		"wrong1": "Auckland",
		"wrong2": "Christchurch",
		"wrong3": "Hamilton",
		"wrong4": "Dunedin",
		"wrong5": "Napier",
		"wrong6": "Tauranga",
		"wrong7": "Rotorua",
		"wrong8": "Palmerston North",
		"wrong9": "Invercargill",
		"wrong10": "Whangarei",
		"wrong11": "Sydney",
		"wrong12": "Melbourne",
		"wrong13": "Brisbane",
		"wrong14": "Adelaide",
		"wrong15": "Perth",
		"wrong16": "Hobart",
		"wrong17": "Canberra",
		"wrong18": "Darwin",
		"wrong19": "Auckland",
		"wrong20": "Christchurch",
		"wrong21": "Melbourne",
		"wrong22": "Sydney",
		"wrong23": "Brisbane",
		"wrong24": "Adelaide",
		"wrong25": "Perth"
	},
	{
		"country": "Finland",
		"capital": "Helsinki",
		"wrong1": "Espoo",
		"wrong2": "Tampere",
		"wrong3": "Oulu",
		"wrong4": "Turku",
		"wrong5": "Jyväskylä",
		"wrong6": "Lahti",
		"wrong7": "Kuopio",
		"wrong8": "Rovaniemi",
		"wrong9": "Pori",
		"wrong10": "Joensuu",
		"wrong11": "Stockholm",
		"wrong12": "Helsinki",
		"wrong13": "Oslo",
		"wrong14": "Tallinn",
		"wrong15": "Riga",
		"wrong16": "Vilnius",
		"wrong17": "Copenhagen",
		"wrong18": "Amsterdam",
		"wrong19": "Vienna",
		"wrong20": "Brussels",
		"wrong21": "Budapest",
		"wrong22": "Warsaw",
		"wrong23": "Prague",
		"wrong24": "Moscow",
		"wrong25": "Bucharest"
	}
]
